{"version":2,"generated_at":"2026-04-16T14:48:37.658235+00:00","article":{"o_id":5850,"title":"Association islamique de la Tidjania de Haute-Volta","newspaper":"L'Observateur","country":"Burkina Faso","pub_date":"1979-10-09","language":"Français","word_count":32,"lexical_richness":0.7812,"readability":56.3367,"nb_pages":1,"lda_label":"imam - mosquée - communauté_musulman - prière - fidèle - hadj","thumbnail":"https://islam.zmo.de/files/medium/d278806003466651b64b57d2c8da1e6ed77ea5ec.jpg"},"entities":[{"o_id":387,"title":"Ramatoulaye","type":"Lieux"},{"o_id":573,"title":"Association Islamique de la Tijâniyya","type":"Organisations"},{"o_id":1181,"title":"Sidi Mohamed Maïga","type":"Personnes"},{"o_id":15831,"title":"Mosquée","type":"Sujets"},{"o_id":109,"title":"Paix","type":"Sujets"},{"o_id":86,"title":"Prière","type":"Sujets"}],"spatial":[{"o_id":387,"name":"Ramatoulaye","lat":13.633333,"lng":-2.316667}],"related_by_entities":[{"o_id":2887,"title":"\"L'islam n'a jamais bafoué le droit de quiconque\"","newspaper":"L'Observateur Paalga","country":"Burkina Faso","date":"2007-04-04","thumbnail":"","shared_count":6,"shared":[15831,387,109]},{"o_id":8428,"title":"Maouloud 87 à Ramatoulaye : le 1er office de Cheick Aboubacar Maïga II","newspaper":"Sidwaya","country":"Burkina Faso","date":"1987-11-09","thumbnail":"https://islam.zmo.de/files/medium/10df085d1b6aa735bdf8e2de0adff3d3eb9afcf4.jpg","shared_count":5,"shared":[15831,387,1181]},{"o_id":5638,"title":"Message du Cheick Sidi Mohamed Maïga","newspaper":"L'Observateur","country":"Burkina Faso","date":"1980-02-05","thumbnail":"https://islam.zmo.de/files/medium/c725891d6c8cd11ec9d9cee380fce69169667065.jpg","shared_count":5,"shared":[15831,387,1181]},{"o_id":6515,"title":"Célébration du Mouloud à Ramatoulaye : des fidèles de plusieurs horizons","newspaper":"Sidwaya","country":"Burkina Faso","date":"1984-12-12","thumbnail":"https://islam.zmo.de/files/medium/533c029af2f4ab13f1564936115a28ef1464f55b.jpg","shared_count":5,"shared":[15831,387,1181]},{"o_id":8479,"title":"Sourgoubila : séjour du Cheick de Ramatoulaye","newspaper":"Sidwaya","country":"Burkina Faso","date":"1995-01-19","thumbnail":"https://islam.zmo.de/files/medium/7b46a1994677586ccda78b1a6017fdfb4ef841b6.jpg","shared_count":4,"shared":[15831,387,109]},{"o_id":2331,"title":"Grande mosquée de Gourcy : la hache de guerre définitivement enterrée","newspaper":"Le Pays","country":"Burkina Faso","date":"2012-09-11","thumbnail":"","shared_count":4,"shared":[15831,387,109]},{"o_id":2390,"title":"Ramadan 2012 : l'unité des musulmans saluée à Ouahigouya, Ramatoulaye et Tansalga","newspaper":"Le Pays","country":"Burkina Faso","date":"2012-08-26","thumbnail":"","shared_count":4,"shared":[15831,387,109]},{"o_id":2401,"title":"Un jour de grande ferveur","newspaper":"Le Pays","country":"Burkina Faso","date":"2010-09-07","thumbnail":"","shared_count":4,"shared":[15831,387,1181]},{"o_id":3306,"title":"La grande mosquée ouvre à nouveau ses portes","newspaper":"Sidwaya","country":"Burkina Faso","date":"2012-09-12","thumbnail":"","shared_count":4,"shared":[15831,387,109]},{"o_id":3350,"title":"Mouloud 2012 : Ramatoulaye tend la main à la jeunesse","newspaper":"Sidwaya","country":"Burkina Faso","date":"2012-02-06","thumbnail":"","shared_count":4,"shared":[15831,387,109]},{"o_id":3461,"title":"Prière pour la paix au Burkina : Maouloud 2014","newspaper":"Sidwaya","country":"Burkina Faso","date":"2014-01-14","thumbnail":"","shared_count":4,"shared":[15831,387,109]},{"o_id":3511,"title":"Mouloud 2015 : Ramatoulaye réfléchit sur l'éducation de la jeunesse","newspaper":"Sidwaya","country":"Burkina Faso","date":"2015-12-25","thumbnail":"","shared_count":4,"shared":[15831,387,109]},{"o_id":5849,"title":"Chez nous : beaucoup d'évènements","newspaper":"L'Observateur","country":"Burkina Faso","date":"1980-01-29","thumbnail":"https://islam.zmo.de/files/medium/7075d95787e023fa1ee507484cd8fe7887a56bf9.jpg","shared_count":4,"shared":[15831,387,1181]},{"o_id":5903,"title":"Invitation du Cheick Sidi Mohamed Maïga","newspaper":"L'Observateur","country":"Burkina Faso","date":"1980-01-23","thumbnail":"https://islam.zmo.de/files/medium/92ebad34ccd2fc885199f0835136c185d3453c58.jpg","shared_count":4,"shared":[15831,387,1181]},{"o_id":6253,"title":"Nuit du Mouloud : à côté de la foi, les festivités / À Ramatoulaye la fête était belle!","newspaper":"Sidwaya","country":"Burkina Faso","date":"2000-06-19","thumbnail":"https://islam.zmo.de/files/medium/9ef51b7f1a53b52946685c610abc92b03ecc5e2d.jpg","shared_count":4,"shared":[15831,387,109]},{"o_id":6395,"title":"Bam : Kongoussi a désormais sa mosquée de vendredi","newspaper":"Sidwaya","country":"Burkina Faso","date":"1999-05-06","thumbnail":"https://islam.zmo.de/files/medium/fc13c41d5d7ae8801475d7a9f1908fcc84a84638.jpg","shared_count":4,"shared":[15831,387,109]},{"o_id":6616,"title":"Célébration du Maouloud à Ramatoulaye : la preuve d'une ferveur religieuse","newspaper":"Sidwaya","country":"Burkina Faso","date":"1994-08-22","thumbnail":"https://islam.zmo.de/files/medium/2d698eb9b029c09d2faccb5a109201665873a552.jpg","shared_count":4,"shared":[15831,387,1181]},{"o_id":5639,"title":"Association islamique de la Tidjania de Haute-Volta","newspaper":"L'Observateur","country":"Burkina Faso","date":"1979-10-04","thumbnail":"https://islam.zmo.de/files/medium/8c6dd81e503d0e4d723e23189eca4ecdebc14144.jpg","shared_count":4,"shared":[387,1181,86]},{"o_id":3135,"title":"IIIe congrès Tidjania : les tidjanites veulent s'unir pour le rayonnement de l'Islam","newspaper":"Sidwaya","country":"Burkina Faso","date":"2009-05-12","thumbnail":"","shared_count":4,"shared":[387,109,86]},{"o_id":8206,"title":"Communauté musulmane : où sont passés les dollars de Kadhafi?","newspaper":"Le Pays","country":"Burkina Faso","date":"2000-07-14","thumbnail":"https://islam.zmo.de/files/medium/57b60c030793bdb8d7549756a4805dcc85b2e57b.jpg","shared_count":3,"shared":[15831,109,86]}],"semantic_neighbors":[{"o_id":5638,"title":"Message du Cheick Sidi Mohamed Maïga","newspaper":"L'Observateur","country":"Burkina Faso","date":"1980-02-05","thumbnail":"https://islam.zmo.de/files/medium/c725891d6c8cd11ec9d9cee380fce69169667065.jpg","similarity":0.8272},{"o_id":5903,"title":"Invitation du Cheick Sidi Mohamed Maïga","newspaper":"L'Observateur","country":"Burkina Faso","date":"1980-01-23","thumbnail":"https://islam.zmo.de/files/medium/92ebad34ccd2fc885199f0835136c185d3453c58.jpg","similarity":0.8053},{"o_id":5626,"title":"La Grande mosquée","newspaper":"L'Observateur","country":"Burkina Faso","date":"1979-04-23","thumbnail":"https://islam.zmo.de/files/medium/f0300552582fd6d50c8180407b544c8fe4d2770d.jpg","similarity":0.7813},{"o_id":5639,"title":"Association islamique de la Tidjania de Haute-Volta","newspaper":"L'Observateur","country":"Burkina Faso","date":"1979-10-04","thumbnail":"https://islam.zmo.de/files/medium/8c6dd81e503d0e4d723e23189eca4ecdebc14144.jpg","similarity":0.7748},{"o_id":6075,"title":"Islam : une mosquée climatisée à Gounghin","newspaper":"Le Pays","country":"Burkina Faso","date":"1998-12-29","thumbnail":"https://islam.zmo.de/files/medium/f6094bf47f5c12858b54b1543be6a22a782e74ce.jpg","similarity":0.7704},{"o_id":77027,"title":"ADO à la grande mosquée de Korhogo","newspaper":"Le Patriote","country":"Côte d'Ivoire","date":"2010-10-09","thumbnail":"","similarity":0.766},{"o_id":8465,"title":"Le Mouloud 86 à Ramatoulaye","newspaper":"Sidwaya","country":"Burkina Faso","date":"1986-11-17","thumbnail":"https://islam.zmo.de/files/medium/b11adb709155391790338e776ffb2fefe843a4cb.jpg","similarity":0.7612},{"o_id":8054,"title":"Erratum","newspaper":"L'Observateur","country":"Burkina Faso","date":"1979-03-14","thumbnail":"https://islam.zmo.de/files/medium/663d772165c2407691dca54f889346f8fe6068e0.jpg","similarity":0.7596},{"o_id":74547,"title":"Ramadan. Alassane Ouattara : “L'Islam est une religion de non-violence”","newspaper":"Le Patriote","country":"Côte d'Ivoire","date":"2015-07-20","thumbnail":"","similarity":0.7577},{"o_id":10088,"title":"Ouahigouya : l'histoire des cheiks de Ramatoulaye","newspaper":"Le Pays","country":"Burkina Faso","date":"1999-06-30","thumbnail":"https://islam.zmo.de/files/medium/2051448c077cd3f440e775d5ec92742514a66505.jpg","similarity":0.7547}]}