{"version":2,"generated_at":"2026-04-16T14:49:18.790783+00:00","article":{"o_id":62694,"title":"Ivoirité, tribalisme, intégriste","newspaper":"Le Patriote","country":"Côte d'Ivoire","pub_date":"1999-08-05","language":"Français","word_count":12,"lexical_richness":1.0,"readability":67.5993,"nb_pages":2,"lda_label":"terrorisme - population - militaire - sahel - terroriste - radio","thumbnail":"https://islam.zmo.de/files/medium/3412345c9395cea44892cb8fe7949d2a02624d71.jpg"},"entities":[{"o_id":298,"title":"Côte d'Ivoire","type":"Lieux"},{"o_id":43055,"title":"Henri Konan Bédié","type":"Personnes"},{"o_id":59,"title":"Intégrisme","type":"Sujets"},{"o_id":43059,"title":"Ivoirité","type":"Sujets"},{"o_id":76268,"title":"Politique","type":"Sujets"},{"o_id":75964,"title":"Tribalisme","type":"Sujets"}],"spatial":[{"o_id":298,"name":"Côte d'Ivoire","lat":8.0,"lng":-5.5}],"related_by_entities":[{"o_id":64798,"title":"Cheick Affou Sanogo (Chef suprême des musulmans de Côte d'Ivoire) : \"Contribuer à raffermir l'unité nationale\"","newspaper":"Fraternité Matin","country":"Côte d'Ivoire","date":"1996-10-04","thumbnail":"https://islam.zmo.de/files/medium/bf12bb9fc30668e53b9d619b664bb301e1153ccb.jpg","shared_count":6,"shared":[298,76268,43055]},{"o_id":48539,"title":"Ivoirité, tribalisme, intégriste","newspaper":"Le Patriote","country":"Côte d'Ivoire","date":"1999-08-05","thumbnail":"https://islam.zmo.de/files/medium/39bfb093be2814195d2c9f34b7776ef01bb63b96.jpg","shared_count":6,"shared":[298,76268,43055]},{"o_id":61423,"title":"Assemblée générale extraordinaire du CNI : quitus pour Koudouss Idrissa Koné","newspaper":"La Voie","country":"Côte d'Ivoire","date":"1995-09-18","thumbnail":"https://islam.zmo.de/files/medium/826cc025df1f55c56aef336cc5b442536630dba5.jpg","shared_count":5,"shared":[298,76268,43055]},{"o_id":62698,"title":"Alassane Drame Ouattara a-t-il un avenir politique en Côte d'Ivoire?","newspaper":"Le Nouvel Horizon","country":"Côte d'Ivoire","date":"1994-01-28","thumbnail":"https://islam.zmo.de/files/medium/fc8ae6628319015ff114fe808878c0cb8a64eb6b.jpg","shared_count":5,"shared":[298,76268,43055]},{"o_id":62721,"title":"Le complot diabolique du PDCI contre le RDR","newspaper":"Le Nouvel Horizon","country":"Côte d'Ivoire","date":"1994-07-22","thumbnail":"https://islam.zmo.de/files/medium/43b48eac5623cf04b082a365c40c510cbbfd594e.jpg","shared_count":5,"shared":[298,76268,43055]},{"o_id":46342,"title":"XVIIe séminaire national de l'AEEMCI : la jeunesse musulmane interpelle Bédié","newspaper":"Notre Voie","country":"Côte d'Ivoire","date":"1999-09-09","thumbnail":"https://islam.zmo.de/files/medium/2c2541598815197b38be1ddbc20c43862625a93b.jpg","shared_count":5,"shared":[298,76268,43055]},{"o_id":48659,"title":"Interview. L'imam El Hadj Idriss Koudouss Koné, chef de la communauté musulmane de Côte d'Ivoire : \"Le retour d'ADO dans le jeu politique est obligatoire\"","newspaper":"Le Patriote","country":"Côte d'Ivoire","date":"2001-02-15","thumbnail":"https://islam.zmo.de/files/medium/839c5edab96a12497fe71fca7fa9b7579d084a31.jpg","shared_count":5,"shared":[298,76268,43055]},{"o_id":76415,"title":"\"Vieux Touré\" (président des musulmans orthodoxes) : \"Bédié pousse le peuple à la lutte armée\"","newspaper":"Le Nouvel Horizon","country":"Côte d'Ivoire","date":"1995-10-13","thumbnail":"https://islam.zmo.de/files/medium/7478df15a9c7c8f7eff3f31488c0980a9d53b210.jpg","shared_count":4,"shared":[298,43055,43059]},{"o_id":68351,"title":"2ème Conseil consultatif du CNI-COSIM samedi à la mosquée de la Riviera : cohésion renforcée","newspaper":"Fraternité Matin","country":"Côte d'Ivoire","date":"1998-11-09","thumbnail":"https://islam.zmo.de/files/medium/04ec1a2bc7621de65612cb96295e64b496132a25.jpg","shared_count":4,"shared":[298,76268,43055]},{"o_id":61380,"title":"Code électoral : crime au nom de l'ivoirité","newspaper":"La Voie","country":"Côte d'Ivoire","date":"1995-02-16","thumbnail":"https://islam.zmo.de/files/medium/e5c41c57a5b0bb508531e44a3e03d7cffd7dacc8.jpg","shared_count":4,"shared":[298,76268,43055]},{"o_id":61585,"title":"Cartes de séjour : musulmans = étrangers?","newspaper":"La Voie","country":"Côte d'Ivoire","date":"1994-06-24","thumbnail":"https://islam.zmo.de/files/medium/348035e88733335d5ba8af7d5a33ef4fad526302.jpg","shared_count":4,"shared":[298,76268,43055]},{"o_id":61587,"title":"Les musulmans de Côte d'Ivoire : des boucs émissaires?","newspaper":"La Voie","country":"Côte d'Ivoire","date":"1994-06-15","thumbnail":"https://islam.zmo.de/files/medium/88e98274a579b5ae60391e94b65e1ff940bad6fc.jpg","shared_count":4,"shared":[298,76268,43059]},{"o_id":61631,"title":"Conseil supérieur islamique (CSI) : Diaby Moustapha \"Koweit\" déjà en campagne pour Bédié","newspaper":"La Voie","country":"Côte d'Ivoire","date":"1993-12-22","thumbnail":"https://islam.zmo.de/files/medium/b2a58a41da292aa623aa503600dbd23d0c7c01ab.jpg","shared_count":4,"shared":[298,76268,43055]},{"o_id":62456,"title":"Conférence du Dr Balla Kéita : \"le RDR n'est pas un parti de musulmans\"","newspaper":"Le Nouvel Horizon","country":"Côte d'Ivoire","date":"1994-12-30","thumbnail":"https://islam.zmo.de/files/medium/5c9dce3ac008036fe3e409f67ac22f58e82f5956.jpg","shared_count":4,"shared":[298,76268,43055]},{"o_id":62692,"title":"Présidence de la République : les représentants des cultes chez Bédié","newspaper":"La Voie","country":"Côte d'Ivoire","date":"1993-12-24","thumbnail":"https://islam.zmo.de/files/medium/012aa213308672cc8a6b543f3d814ebad3250a1f.jpg","shared_count":4,"shared":[298,76268,43055]},{"o_id":62700,"title":"Diaby \"Koweït\" à propos du procès CSI-CNI : \"Je ne suis pas au courant\"","newspaper":"Fraternité Matin","country":"Côte d'Ivoire","date":"1994-09-05","thumbnail":"https://islam.zmo.de/files/medium/7a449670111e48434c864ca64b4badc1bdf5b204.jpg","shared_count":4,"shared":[298,76268,43055]},{"o_id":62723,"title":"Diaby Koweit : manipulé ou manipulateur?","newspaper":"Le Nouvel Horizon","country":"Côte d'Ivoire","date":"1994-03-04","thumbnail":"https://islam.zmo.de/files/medium/4c5293eba4852a7971ce20078a6089bb86e7f881.jpg","shared_count":4,"shared":[298,76268,43055]},{"o_id":62724,"title":"Halte à la division des musulmans","newspaper":"Le Patriote","country":"Côte d'Ivoire","date":"1994-01-21","thumbnail":"https://islam.zmo.de/files/medium/27fb2bfdd80db3cf3673b00ec2941192b44fbbb1.jpg","shared_count":4,"shared":[298,76268,43055]},{"o_id":62728,"title":"Henriette Dagri Diabité, secrétaire général par intérim du RDR : \"On accable les musulmans pour rien\"","newspaper":"Le Jour","country":"Côte d'Ivoire","date":"1998-12-31","thumbnail":"https://islam.zmo.de/files/medium/44eabd1e4415bafa316ee684d81caf6a16948be9.jpg","shared_count":4,"shared":[298,76268,43055]},{"o_id":46350,"title":"Après l'ivoirité, le \"rattrapage\" ethnique, les concepts ségrégationnistes de Ouattara et Bédié","newspaper":"Notre Voie","country":"Côte d'Ivoire","date":"2012-06-12","thumbnail":"","shared_count":4,"shared":[298,76268,43055]}],"semantic_neighbors":[{"o_id":62378,"title":"La Tabaski","newspaper":"Fraternité Hebdo","country":"Côte d'Ivoire","date":"1977-11-25","thumbnail":"https://islam.zmo.de/files/medium/e902f60fcb1f5293941f5e36d2147ab25f7fc170.jpg","similarity":0.7419},{"o_id":48741,"title":"ADO a prié à la Riviera","newspaper":"Le Patriote","country":"Côte d'Ivoire","date":"2001-12-17","thumbnail":"https://islam.zmo.de/files/medium/0b015491f155408b3db54657d6e3749f3ba4d69a.jpg","similarity":0.7368},{"o_id":63863,"title":"Justice : Hamed Bakayoko au tribunal ce matin","newspaper":"Fraternité Matin","country":"Côte d'Ivoire","date":"1994-02-24","thumbnail":"https://islam.zmo.de/files/medium/3e82cd510a87f9610663705f58189561e9a94a28.jpg","similarity":0.7356},{"o_id":63985,"title":"Hier en présence du Chef de l'État : prières pour le repos de l'âme de El Hadj Lanciné Cissé","newspaper":"Fraternité Matin","country":"Côte d'Ivoire","date":"1994-08-13","thumbnail":"https://islam.zmo.de/files/medium/158858044d11732f86add2a49a1e8b2e935723b8.jpg","similarity":0.732},{"o_id":62379,"title":"Musulmans et chrétiens fêtent ensemble Noël et la Tabaski","newspaper":"Fraternité Hebdo","country":"Côte d'Ivoire","date":"1974-12-27","thumbnail":"https://islam.zmo.de/files/medium/d3827dc646a1ba75bbe3229fb2103774b176aec7.jpg","similarity":0.7318},{"o_id":61545,"title":"Séminaire SENAFOP à Baouké","newspaper":"La Voie","country":"Côte d'Ivoire","date":"1994-09-24","thumbnail":"https://islam.zmo.de/files/medium/4168aecebe278025221123ea208ea3d11e6ee293.jpg","similarity":0.7309},{"o_id":62364,"title":"Hier à Abobo : les musulmans ont prié pour le Chef de l'État","newspaper":"Fraternité Matin","country":"Côte d'Ivoire","date":"1990-05-08","thumbnail":"https://islam.zmo.de/files/medium/931a689d09ab1ea93591a3c31fc4ca0ae368c3b0.jpg","similarity":0.7298},{"o_id":63944,"title":"Complot à trois têtes : la désinformation","newspaper":"Fraternité Matin","country":"Côte d'Ivoire","date":"1994-12-22","thumbnail":"https://islam.zmo.de/files/medium/2c344ee1b8d96a0a00b15d67a4be99dc555515ea.jpg","similarity":0.7284},{"o_id":63860,"title":"Hamed Bakayoko à la MACA : dans l'indifférence","newspaper":"Fraternité Matin","country":"Côte d'Ivoire","date":"1994-03-08","thumbnail":"https://islam.zmo.de/files/medium/c62681824b9632cc60bf39d005054fdae81488d1.jpg","similarity":0.7268},{"o_id":48625,"title":"En campagne électorale à Koumassi : le Pr Mamadou Koulibaly s'en prend aux imams","newspaper":"Le Patriote","country":"Côte d'Ivoire","date":"2000-12-11","thumbnail":"https://islam.zmo.de/files/medium/502eee120397b0c4448214146a7b52e40761cfc5.jpg","similarity":0.7265}]}